datadistillr/__init__.py
datadistillr/auth_exceptions.py
datadistillr/datadistillr.py
datadistillr/datadistillr_account.py
datadistillr/project.py
datadistillr/tests/__init__.py
datadistillr/tests/test_datadistillr_account.py
datadistillr/tests/test_datadistillr_api.py
datadistillr/tests/test_project.py
datadistillr-1.0.1.dist-info/LICENSE
datadistillr-1.0.1.dist-info/METADATA
datadistillr-1.0.1.dist-info/WHEEL
datadistillr-1.0.1.dist-info/top_level.txt
datadistillr-1.0.1.dist-info/RECORD
