Metadata-Version: 2.1
Name: datadistillr
Version: 1.0.1
Summary: A Python SDK for interacting with datasets created on DataDistillr
Home-page: https://github.com/datadistillr/datadistillr-python-sdk
Author: Charles Givre, Amanda Ha, Andrea Ha, Sanaa Mironov
Author-email: charles@datadistillr.com
License: Apache
Classifier: Intended Audience :: Developers
Classifier: Intended Audience :: System Administrators
Classifier: Intended Audience :: Science/Research
Classifier: License :: OSI Approved :: Apache Software License
Classifier: Programming Language :: Python
Classifier: Programming Language :: Python :: 3
Classifier: Programming Language :: SQL
Classifier: Operating System :: OS Independent
Classifier: Topic :: Database
License-File: LICENSE
Requires-Dist: pandas
Requires-Dist: requests
Requires-Dist: urllib3
